<?xml version="1.0" encoding="utf-8" ?>
<c2eventsheet>
    <!--All the 'name' attributes are ignored by Construct 2 - they are there for readability only.-->
    <name>GameWonEV</name>
    <events>
        <event-group description="" sid="5753716612449855" title="Start of Layout" />
        <event-block sid="704980216663693">
            <conditions>
                <condition id="-2" name="On start of layout" sid="9297473244210386" type="System" />
            </conditions>
            <actions>
                <action id="33" name="Stop all" sid="9034878992621095" type="Audio" />
                <action id="0" name="Play" sid="8856733931190315" type="Audio">
                    <param id="0" name="Audio file">Polarized</param>
                    <param id="2" name="Loop">1</param>
                    <param id="3" name="Volume">0</param>
                    <param id="1" name="Tag (optional)">&quot;&quot;</param>
                </action>
            </actions>
        </event-block>
        <event-group description="" sid="2498795061017766" title="Scoring / Submit" />
        <event-block sid="1534468443689559">
            <conditions>
                <condition id="-1" name="Every tick" sid="3808488320126652" type="System" />
            </conditions>
            <actions>
                <action id="0" name="Set text" sid="5004489260282107" type="PlayerScore">
                    <param id="0" name="Text">&quot;Your Time:&quot; &amp; round((timer2)*100)/100</param>
                </action>
            </actions>
        </event-block>
        <event-block sid="9561147065343474">
            <conditions>
                <condition id="3" name="On touched object" sid="3658011565193067" type="Touch">
                    <param id="0" name="Object">Submit</param>
                </condition>
            </conditions>
            <actions>
                <action id="2" name="Post to URL" sid="336018512209131" type="AJAX">
                    <param id="0" name="Tag">&quot;PostScore&quot;</param>
                    <param id="1" name="URL">&quot;http://www.meowzergames.com/cgi-bin/savescores.php?name=&quot;&amp;txtPlayerName.Text &amp; &quot;&amp;level=&quot;&amp;Level &amp; &quot;&amp;score=&quot;&amp;Score</param>
                    <param id="2" name="Data">&quot;&quot;</param>
                    <param id="3" name="Method">&quot;POST&quot;</param>
                </action>
            </actions>
            <sub-events>
                <event-block sid="9874146569402558">
                    <conditions />
                    <actions>
                        <action id="-9" name="Destroy" sid="9555799536002653" type="Submit" />
                        <action id="-9" name="Destroy" sid="5053543312021657" type="txtPlayerName" />
                    </actions>
                </event-block>
            </sub-events>
        </event-block>
        <event-block sid="943489618032448">
            <conditions>
                <condition id="-2" name="On start of layout" sid="8188011909917505" type="System" />
            </conditions>
            <actions>
                <action id="0" name="Request URL" sid="5256449690750207" type="AJAX">
                    <param id="0" name="Tag">&quot;GetScores&quot;</param>
                    <param id="1" name="URL">&quot;http://www.meowzergames.com/cgi-bin/getscores.php&quot;</param>
                </action>
            </actions>
        </event-block>
        <event-block sid="4609268985059341">
            <conditions>
                <condition id="0" name="On completed" sid="1588712029784417" type="AJAX">
                    <param id="0" name="Tag">&quot;GetScores&quot;</param>
                </condition>
            </conditions>
            <actions>
                <action id="-12" name="Set group active" sid="6078772639169257" type="System">
                    <param id="0" name="Group name">&quot;Do Array2&quot;</param>
                    <param id="1" name="State">1</param>
                </action>
            </actions>
        </event-block>
        <event-block sid="3095336505166219">
            <conditions>
                <condition id="0" name="On completed" sid="6915264914619349" type="AJAX">
                    <param id="0" name="Tag">&quot;PostScore&quot;</param>
                </condition>
            </conditions>
            <actions>
                <action id="0" name="Request URL" sid="6193799367812744" type="AJAX">
                    <param id="0" name="Tag">&quot;GetScores&quot;</param>
                    <param id="1" name="URL">&quot;http://www.meowzergames.com/cgi-bin/getscores.php&quot;</param>
                </action>
            </actions>
        </event-block>
        <event-group description="" sid="2151466982977166" title="Do Array2">
            <sub-events>
                <event-block sid="9795451878638472">
                    <conditions>
                        <condition id="3" name="For each element" sid="7735824144202104" type="Array">
                            <param id="0" name="Axes">2</param>
                        </condition>
                    </conditions>
                    <actions>
                        <action id="2" name="Set at X" sid="4185396709572948" type="Array">
                            <param id="0" name="X">Array.CurX</param>
                            <param id="1" name="Value">tokenat(Ajax.LastData,Array.CurX, &quot;|&quot;)</param>
                        </action>
                    </actions>
                </event-block>
                <event-block sid="865398280604588">
                    <conditions>
                        <condition id="-11" name="For Each" sid="1916331088043738" type="System">
                            <param id="0" name="Object">Text</param>
                        </condition>
                    </conditions>
                    <actions>
                        <action id="0" name="Set text" sid="5984711155709667" type="Text">
                            <param id="0" name="Text">Array.At(Text.IID)</param>
                        </action>
                    </actions>
                </event-block>
                <event-block sid="7696031650793038">
                    <conditions />
                    <actions>
                        <action id="-12" name="Set group active" sid="1643288183082004" type="System">
                            <param id="0" name="Group name">&quot;Do Array2&quot;</param>
                            <param id="1" name="State">0</param>
                        </action>
                    </actions>
                </event-block>
            </sub-events>
        </event-group>
        <event-block sid="348909820237588">
            <conditions>
                <condition id="-3" name="Is on-screen" sid="8112013191632613" type="txtPlayerName" />
            </conditions>
            <actions>
                <action id="7" name="Set CSS style" sid="8631157021598156" type="txtPlayerName">
                    <param id="0" name="Property name">&quot;color&quot;</param>
                    <param id="1" name="Value">&quot;black&quot;</param>
                </action>
                <action id="7" name="Set CSS style" sid="5949144177635863" type="txtPlayerName">
                    <param id="0" name="Property name">&quot;background&quot;</param>
                    <param id="1" name="Value">&quot;#57CAFA&quot;</param>
                </action>
                <action id="7" name="Set CSS style" sid="6453307018916194" type="txtPlayerName">
                    <param id="0" name="Property name">&quot;web font&quot;</param>
                    <param id="1" name="Value">&quot;snap itc&quot; </param>
                </action>
                <action id="7" name="Set CSS style" sid="3296091688864457" type="txtPlayerName">
                    <param id="0" name="Property name">&quot;font-size&quot;</param>
                    <param id="1" name="Value">&quot;3em&quot;</param>
                </action>
            </actions>
        </event-block>
        <event-group description="" sid="943687378945592" title="Menu/Retry/Next Buttons" />
        <comment>Menu Button</comment>
        <event-block sid="8592383876629076">
            <conditions>
                <condition id="2" name="Is in touch" sid="5300099631818223" type="Touch" />
            </conditions>
            <actions>
                <action id="-16" name="Wait" sid="1439619609139678" type="System">
                    <param id="0" name="Seconds">0.5</param>
                </action>
            </actions>
        </event-block>
        <event-block sid="4604356096422082">
            <conditions>
                <condition id="4" name="Is touching object" sid="2422523721502739" type="Touch">
                    <param id="0" name="Object">NextLevel</param>
                </condition>
                <condition id="-7" name="Compare instance variable" sid="3480874337640392" type="NextLevel">
                    <param id="0" name="Instance variable">grow</param>
                    <param id="1" name="Comparison">0</param>
                    <param id="2" name="Value">1</param>
                </condition>
            </conditions>
            <actions>
                <action id="-11" name="Add to" sid="7587753103650756" type="NextLevel">
                    <param id="0" name="Instance variable">scale</param>
                    <param id="1" name="Value">0.08</param>
                </action>
                <action id="9" name="Set scale" sid="9929675622212733" type="NextLevel">
                    <param id="0" name="Scale">NextLevel.scale</param>
                </action>
                <action id="0" name="Play" sid="9183783788312761" type="Audio">
                    <param id="0" name="Audio file">Menu buttons</param>
                    <param id="2" name="Loop">0</param>
                    <param id="3" name="Volume">-15</param>
                    <param id="1" name="Tag (optional)">&quot;&quot;</param>
                </action>
            </actions>
            <sub-events>
                <event-block sid="9661817419089458">
                    <conditions>
                        <condition id="-7" name="Compare instance variable" sid="9458065287659827" type="NextLevel">
                            <param id="0" name="Instance variable">scale</param>
                            <param id="1" name="Comparison">5</param>
                            <param id="2" name="Value">1.2</param>
                        </condition>
                    </conditions>
                    <actions>
                        <action id="-10" name="Set value" sid="9448038878924372" type="NextLevel">
                            <param id="0" name="Instance variable">grow</param>
                            <param id="1" name="Value">0</param>
                        </action>
                    </actions>
                </event-block>
            </sub-events>
        </event-block>
        <event-block sid="5041711187214252">
            <conditions>
                <condition id="2" inverted="1" name="Is in touch" sid="5054135302658482" type="Touch" />
            </conditions>
            <actions>
                <action id="-10" name="Set value" sid="3607556827506177" type="NextLevel">
                    <param id="0" name="Instance variable">scale</param>
                    <param id="1" name="Value">1</param>
                </action>
                <action id="-10" name="Set value" sid="8790632126438259" type="NextLevel">
                    <param id="0" name="Instance variable">grow</param>
                    <param id="1" name="Value">1</param>
                </action>
                <action id="9" name="Set scale" sid="3218035212701376" type="NextLevel">
                    <param id="0" name="Scale">1</param>
                </action>
            </actions>
        </event-block>
        <comment>Next Level Button</comment>
        <event-block sid="744426912644021">
            <conditions>
                <condition id="3" name="On touched object" sid="1859546025244279" type="Touch">
                    <param id="0" name="Object">HomeButton</param>
                </condition>
            </conditions>
            <actions>
                <action id="-16" name="Wait" sid="8904728374004313" type="System">
                    <param id="0" name="Seconds">0.5</param>
                </action>
                <action id="-2" name="Go to layout" sid="6010572067981085" type="System">
                    <param id="0" name="Layout">MenuScreen</param>
                </action>
                <action id="-21" name="Reset global variables" sid="156314269962477" type="System" />
            </actions>
        </event-block>
        <event-block sid="2788462886413704">
            <conditions>
                <condition id="4" name="Is touching object" sid="1248337188580509" type="Touch">
                    <param id="0" name="Object">HomeButton</param>
                </condition>
                <condition id="-7" name="Compare instance variable" sid="8748858165638062" type="HomeButton">
                    <param id="0" name="Instance variable">grow</param>
                    <param id="1" name="Comparison">0</param>
                    <param id="2" name="Value">1</param>
                </condition>
            </conditions>
            <actions>
                <action id="-11" name="Add to" sid="7580505371941657" type="HomeButton">
                    <param id="0" name="Instance variable">scale</param>
                    <param id="1" name="Value">0.08</param>
                </action>
                <action id="9" name="Set scale" sid="8811233598839913" type="HomeButton">
                    <param id="0" name="Scale">HomeButton.scale</param>
                </action>
                <action id="0" name="Play" sid="3243228166781698" type="Audio">
                    <param id="0" name="Audio file">Menu buttons</param>
                    <param id="2" name="Loop">0</param>
                    <param id="3" name="Volume">-15</param>
                    <param id="1" name="Tag (optional)">&quot;&quot;</param>
                </action>
            </actions>
            <sub-events>
                <event-block sid="7558657330922092">
                    <conditions>
                        <condition id="-7" name="Compare instance variable" sid="3737932438641612" type="HomeButton">
                            <param id="0" name="Instance variable">scale</param>
                            <param id="1" name="Comparison">5</param>
                            <param id="2" name="Value">1.2</param>
                        </condition>
                    </conditions>
                    <actions>
                        <action id="-10" name="Set value" sid="792297137179571" type="HomeButton">
                            <param id="0" name="Instance variable">grow</param>
                            <param id="1" name="Value">0</param>
                        </action>
                    </actions>
                </event-block>
            </sub-events>
        </event-block>
        <event-block sid="6470622564367344">
            <conditions>
                <condition id="2" inverted="1" name="Is in touch" sid="9236929995353898" type="Touch" />
            </conditions>
            <actions>
                <action id="-10" name="Set value" sid="8672779364093741" type="HomeButton">
                    <param id="0" name="Instance variable">scale</param>
                    <param id="1" name="Value">1</param>
                </action>
                <action id="-10" name="Set value" sid="3173803181938718" type="HomeButton">
                    <param id="0" name="Instance variable">grow</param>
                    <param id="1" name="Value">1</param>
                </action>
                <action id="9" name="Set scale" sid="8494741160517637" type="HomeButton">
                    <param id="0" name="Scale">1</param>
                </action>
            </actions>
        </event-block>
        <event-block sid="9679031647029089">
            <conditions>
                <condition id="3" name="On touched object" sid="34879049683064" type="Touch">
                    <param id="0" name="Object">NextLevel</param>
                </condition>
            </conditions>
            <actions>
                <action id="-10" name="Add to" sid="3506308541735423" type="System">
                    <param id="0" name="Variable">ProperSelect</param>
                    <param id="1" name="Value">1</param>
                </action>
            </actions>
            <sub-events>
                <event-block sid="3864720182079039">
                    <conditions>
                        <condition id="-14" name="Compare variable" sid="7433504408588786" type="System">
                            <param id="0" name="Variable">ProperSelect</param>
                            <param id="1" name="Comparison">0</param>
                            <param id="2" name="Value">2</param>
                        </condition>
                    </conditions>
                    <actions>
                        <action id="-2" name="Go to layout" sid="3661925078056839" type="System">
                            <param id="0" name="Layout">AddLvl2</param>
                        </action>
                    </actions>
                </event-block>
                <event-block sid="5660796638679214">
                    <conditions>
                        <condition id="-14" name="Compare variable" sid="9956147352430162" type="System">
                            <param id="0" name="Variable">ProperSelect</param>
                            <param id="1" name="Comparison">0</param>
                            <param id="2" name="Value">3</param>
                        </condition>
                    </conditions>
                    <actions>
                        <action id="-2" name="Go to layout" sid="8034724126831887" type="System">
                            <param id="0" name="Layout">SubLvl1</param>
                        </action>
                    </actions>
                </event-block>
                <event-block sid="1082250978994446">
                    <conditions>
                        <condition id="-14" name="Compare variable" sid="5394110090642238" type="System">
                            <param id="0" name="Variable">ProperSelect</param>
                            <param id="1" name="Comparison">0</param>
                            <param id="2" name="Value">4</param>
                        </condition>
                    </conditions>
                    <actions>
                        <action id="-2" name="Go to layout" sid="877179647832213" type="System">
                            <param id="0" name="Layout">SubLvl2</param>
                        </action>
                    </actions>
                </event-block>
                <event-block sid="941264076373967">
                    <conditions>
                        <condition id="-14" name="Compare variable" sid="7186579245510653" type="System">
                            <param id="0" name="Variable">ProperSelect</param>
                            <param id="1" name="Comparison">0</param>
                            <param id="2" name="Value">5</param>
                        </condition>
                    </conditions>
                    <actions>
                        <action id="-2" name="Go to layout" sid="6773962765220421" type="System">
                            <param id="0" name="Layout">AddSubLvl1</param>
                        </action>
                    </actions>
                </event-block>
                <event-block sid="9506888895329239">
                    <conditions>
                        <condition id="-14" name="Compare variable" sid="1271949467266414" type="System">
                            <param id="0" name="Variable">ProperSelect</param>
                            <param id="1" name="Comparison">0</param>
                            <param id="2" name="Value">6</param>
                        </condition>
                    </conditions>
                    <actions>
                        <action id="-2" name="Go to layout" sid="9201730200249281" type="System">
                            <param id="0" name="Layout">AddSubLvl2</param>
                        </action>
                    </actions>
                </event-block>
            </sub-events>
        </event-block>
        <comment>Restart button</comment>
        <event-block sid="8780889761887556">
            <conditions>
                <condition id="3" name="On touched object" sid="496127254815079" type="Touch">
                    <param id="0" name="Object">RestartGame</param>
                </condition>
                <condition id="-7" name="Compare instance variable" sid="9946210330504955" type="RestartGame">
                    <param id="0" name="Instance variable">grow</param>
                    <param id="1" name="Comparison">0</param>
                    <param id="2" name="Value">1</param>
                </condition>
            </conditions>
            <actions>
                <action id="-11" name="Add to" sid="1277731799143367" type="RestartGame">
                    <param id="0" name="Instance variable">scale</param>
                    <param id="1" name="Value">0.08</param>
                </action>
                <action id="9" name="Set scale" sid="2019071378176701" type="RestartGame">
                    <param id="0" name="Scale">RestartGame.scale</param>
                </action>
                <action id="0" name="Play" sid="4804201714798375" type="Audio">
                    <param id="0" name="Audio file">Menu buttons</param>
                    <param id="2" name="Loop">0</param>
                    <param id="3" name="Volume">0</param>
                    <param id="1" name="Tag (optional)">&quot;&quot;</param>
                </action>
            </actions>
            <sub-events>
                <event-block sid="6883345129527385">
                    <conditions>
                        <condition id="-7" name="Compare instance variable" sid="7318075572498738" type="RestartGame">
                            <param id="0" name="Instance variable">scale</param>
                            <param id="1" name="Comparison">5</param>
                            <param id="2" name="Value">1.2</param>
                        </condition>
                    </conditions>
                    <actions>
                        <action id="-10" name="Set value" sid="9440788430280275" type="RestartGame">
                            <param id="0" name="Instance variable">grow</param>
                            <param id="1" name="Value">0</param>
                        </action>
                    </actions>
                </event-block>
            </sub-events>
        </event-block>
        <event-block sid="7114431760144855">
            <conditions>
                <condition id="2" inverted="1" name="Is in touch" sid="5870388607057197" type="Touch" />
            </conditions>
            <actions>
                <action id="-10" name="Set value" sid="2990485691311367" type="RestartGame">
                    <param id="0" name="Instance variable">scale</param>
                    <param id="1" name="Value">1</param>
                </action>
                <action id="-10" name="Set value" sid="9281149190398364" type="RestartGame">
                    <param id="0" name="Instance variable">grow</param>
                    <param id="1" name="Value">1</param>
                </action>
                <action id="9" name="Set scale" sid="1365758689416543" type="RestartGame">
                    <param id="0" name="Scale">1</param>
                </action>
            </actions>
        </event-block>
        <event-block sid="1009179571249187">
            <conditions>
                <condition id="3" name="On touched object" sid="5723760629304158" type="Touch">
                    <param id="0" name="Object">RestartGame</param>
                </condition>
            </conditions>
            <actions>
                <action id="-16" name="Wait" sid="7034581487102334" type="System">
                    <param id="0" name="Seconds">0.5</param>
                </action>
            </actions>
            <sub-events>
                <event-block sid="4607925634705752">
                    <conditions>
                        <condition id="-14" name="Compare variable" sid="3980528179023506" type="System">
                            <param id="0" name="Variable">ProperSelect</param>
                            <param id="1" name="Comparison">0</param>
                            <param id="2" name="Value">1</param>
                        </condition>
                    </conditions>
                    <actions>
                        <action id="-2" name="Go to layout" sid="3580330638016497" type="System">
                            <param id="0" name="Layout">AddLvl1</param>
                        </action>
                    </actions>
                </event-block>
                <event-block sid="430512993944741">
                    <conditions>
                        <condition id="-14" name="Compare variable" sid="1780040663453428" type="System">
                            <param id="0" name="Variable">ProperSelect</param>
                            <param id="1" name="Comparison">0</param>
                            <param id="2" name="Value">2</param>
                        </condition>
                    </conditions>
                    <actions>
                        <action id="-2" name="Go to layout" sid="9969321933043406" type="System">
                            <param id="0" name="Layout">AddLvl2</param>
                        </action>
                    </actions>
                </event-block>
                <event-block sid="8446099129921237">
                    <conditions>
                        <condition id="-14" name="Compare variable" sid="8336602446986911" type="System">
                            <param id="0" name="Variable">ProperSelect</param>
                            <param id="1" name="Comparison">0</param>
                            <param id="2" name="Value">3</param>
                        </condition>
                    </conditions>
                    <actions>
                        <action id="-2" name="Go to layout" sid="4216125174468177" type="System">
                            <param id="0" name="Layout">SubLvl1</param>
                        </action>
                    </actions>
                </event-block>
                <event-block sid="3245512872339565">
                    <conditions>
                        <condition id="-14" name="Compare variable" sid="3941740263165101" type="System">
                            <param id="0" name="Variable">ProperSelect</param>
                            <param id="1" name="Comparison">0</param>
                            <param id="2" name="Value">4</param>
                        </condition>
                    </conditions>
                    <actions>
                        <action id="-2" name="Go to layout" sid="7498606482029531" type="System">
                            <param id="0" name="Layout">SubLvl2</param>
                        </action>
                    </actions>
                </event-block>
                <event-block sid="3051498618876405">
                    <conditions>
                        <condition id="-14" name="Compare variable" sid="3903200475967612" type="System">
                            <param id="0" name="Variable">ProperSelect</param>
                            <param id="1" name="Comparison">0</param>
                            <param id="2" name="Value">5</param>
                        </condition>
                    </conditions>
                    <actions>
                        <action id="-2" name="Go to layout" sid="3150010948851224" type="System">
                            <param id="0" name="Layout">AddSubLvl1</param>
                        </action>
                    </actions>
                </event-block>
                <event-block sid="2880614227158708">
                    <conditions>
                        <condition id="-14" name="Compare variable" sid="9892566481828607" type="System">
                            <param id="0" name="Variable">ProperSelect</param>
                            <param id="1" name="Comparison">0</param>
                            <param id="2" name="Value">6</param>
                        </condition>
                    </conditions>
                    <actions>
                        <action id="-2" name="Go to layout" sid="7224084034795286" type="System">
                            <param id="0" name="Layout">AddSubLvl2</param>
                        </action>
                    </actions>
                </event-block>
            </sub-events>
        </event-block>
    </events>
</c2eventsheet>
